MANIFEST.in
requirements.txt
setup.py
quotation/Engine.py
quotation/__init__.py
quotation/api.py
quotation/eq.py
quotation/ts.py
quotation/utills.py
quotation.egg-info/PKG-INFO
quotation.egg-info/SOURCES.txt
quotation.egg-info/dependency_links.txt
quotation.egg-info/not-zip-safe
quotation.egg-info/requires.txt
quotation.egg-info/top_level.txt