Metadata-Version: 1.1
Name: quotation
Version: 0.0.1
Summary: A simple package to get real-time chinese stock quotation
Home-page: https://github.com/Cuizi7/quotation
Author: Cuizi7
Author-email: UNKNOWN
License: UNKNOWN
Platform: UNKNOWN
Classifier: Programming Language :: Python :: 3
Classifier: Programming Language :: Python :: 3.4
Classifier: Programming Language :: Python :: 3.5
